rfmix_reader/__init__.py
rfmix_reader/_testing.py
rfmix_reader/base.svg.p
rfmix_reader/cli/__init__.py
rfmix_reader/cli/create_binaries.py
rfmix_reader/cli/merge_phased_zarrs.py
rfmix_reader/cli/prepare_reference.py
rfmix_reader/io/__init__.py
rfmix_reader/io/chunk.py
rfmix_reader/io/errors.py
rfmix_reader/io/loci_bed.py
rfmix_reader/io/prepare_reference.py
rfmix_reader/io/write_data.py
rfmix_reader/processing/__init__.py
rfmix_reader/processing/_hmm_lai.py
rfmix_reader/processing/constants.py
rfmix_reader/processing/imputation.py
rfmix_reader/processing/phase.py
rfmix_reader/readers/__init__.py
rfmix_reader/readers/fb_read.py
rfmix_reader/readers/read_flare.py
rfmix_reader/readers/read_rfmix.py
rfmix_reader/readers/read_simu.py
rfmix_reader/utils.py
rfmix_reader/viz/__init__.py
rfmix_reader/viz/tagore.py
rfmix_reader/viz/visualization.py
rfmix_reader-0.3.1.dist-info/METADATA
rfmix_reader-0.3.1.dist-info/WHEEL
rfmix_reader-0.3.1.dist-info/entry_points.txt
rfmix_reader-0.3.1.dist-info/licenses/LICENSE
rfmix_reader-0.3.1.dist-info/RECORD
