Metadata-Version: 2.4
Name: rfmix-reader
Version: 0.3.1
Summary: RFMix-reader is a Python package designed to efficiently read and process output files generated by RFMix, a popular tool for estimating local ancestry in admixed populations. The package employs a lazy loading approach, which minimizes memory consumption by reading only the loci that are accessed by the user, rather than loading the entire dataset into memory at once.
License: GPL-3.0-or-later
License-File: LICENSE
Keywords: file parser,rfmix,gpu acceleration,local ancestry
Author: Kynon J.M. Benjamin
Author-email: kj.benjamin90@gmail.com
Maintainer: Kynon J.M. Benjamin
Maintainer-email: kj.benjamin90@gmail.com
Requires-Python: >=3.11,<3.15
Classifier: License :: OSI Approved :: GNU General Public License v3 or later (GPLv3+)
Classifier: Operating System :: OS Independent
Classifier: Programming Language :: Python :: 3
Classifier: Programming Language :: Python :: 3.11
Classifier: Programming Language :: Python :: 3.12
Classifier: Programming Language :: Python :: 3.13
Classifier: Programming Language :: Python :: 3.14
Provides-Extra: all
Provides-Extra: docs
Provides-Extra: gpu
Provides-Extra: io
Provides-Extra: tests
Provides-Extra: viz
Requires-Dist: cairosvg (>=2.7,<3.0) ; extra == "viz" or extra == "all"
Requires-Dist: cudf-cu12 ; extra == "all"
Requires-Dist: cupy-cuda12x ; extra == "all"
Requires-Dist: cyvcf2 (>=0.31)
Requires-Dist: dask (>=2025.1,<2026.0)
Requires-Dist: dask-cudf-cu12 ; extra == "all"
Requires-Dist: fonttools (>=4.61.0,<5.0.0)
Requires-Dist: matplotlib (>=3.10,<4.0) ; extra == "viz" or extra == "all"
Requires-Dist: numpy (>=1.23,<3)
Requires-Dist: pandas (>=2.0)
Requires-Dist: psutil (>=7,<8)
Requires-Dist: pyarrow ; extra == "io" or extra == "all"
Requires-Dist: seaborn (>=0.13,<0.14) ; extra == "viz" or extra == "all"
Requires-Dist: sphinx (>=7,<9) ; extra == "docs"
Requires-Dist: sphinx-autodoc-typehints (>=2,<3) ; extra == "docs"
Requires-Dist: sphinx-copybutton (>=0.5,<0.6) ; extra == "docs"
Requires-Dist: sphinx-rtd-theme (>=2,<3) ; extra == "docs"
Requires-Dist: torch (>=2.8) ; extra == "gpu" or extra == "all"
Requires-Dist: tqdm (>=4.66)
Project-URL: Bug Tracker, https://github.com/heart-gen/rfmix_reader/issues
Project-URL: homepage, https://rfmix-reader.readthedocs.io/en/latest/
Project-URL: repository, https://github.com/heart-gen/rfmix_reader.git
